odoo/addons/l10n_es_facturae_face/README.rst
odoo/addons/l10n_es_facturae_face/__init__.py
odoo/addons/l10n_es_facturae_face/__manifest__.py
odoo/addons/l10n_es_facturae_face/components/__init__.py
odoo/addons/l10n_es_facturae_face/components/account_move_l10n_es_facturae_face_listener.py
odoo/addons/l10n_es_facturae_face/components/account_move_l10n_es_facturae_listener.py
odoo/addons/l10n_es_facturae_face/components/edi_input_process_l10n_es_facturae_l10n_es_facturae_face_update.py
odoo/addons/l10n_es_facturae_face/components/edi_send_l10n_es_facturae_face.py
odoo/addons/l10n_es_facturae_face/components/edi_send_l10n_es_facturae_face_cancel.py
odoo/addons/l10n_es_facturae_face/components/edi_webservice_receive_face_l10n_es_facturae_face_update.py
odoo/addons/l10n_es_facturae_face/components/webservice_face.py
odoo/addons/l10n_es_facturae_face/data/cron_data.xml
odoo/addons/l10n_es_facturae_face/data/edi.xml
odoo/addons/l10n_es_facturae_face/data/face_data.xml
odoo/addons/l10n_es_facturae_face/i18n/ca.po
odoo/addons/l10n_es_facturae_face/i18n/es.po
odoo/addons/l10n_es_facturae_face/i18n/l10n_es_facturae_face.pot
odoo/addons/l10n_es_facturae_face/models/__init__.py
odoo/addons/l10n_es_facturae_face/models/account_move.py
odoo/addons/l10n_es_facturae_face/models/edi_exchange_record.py
odoo/addons/l10n_es_facturae_face/models/res_company.py
odoo/addons/l10n_es_facturae_face/models/res_partner.py
odoo/addons/l10n_es_facturae_face/models/wsse_signature.py
odoo/addons/l10n_es_facturae_face/readme/CONFIGURE.md
odoo/addons/l10n_es_facturae_face/readme/CONTRIBUTORS.md
odoo/addons/l10n_es_facturae_face/readme/DESCRIPTION.md
odoo/addons/l10n_es_facturae_face/readme/USAGE.md
odoo/addons/l10n_es_facturae_face/security/ir.model.access.csv
odoo/addons/l10n_es_facturae_face/static/description/icon.png
odoo/addons/l10n_es_facturae_face/static/description/index.html
odoo/addons/l10n_es_facturae_face/tests/__init__.py
odoo/addons/l10n_es_facturae_face/tests/test_facturae_face.py
odoo_addon_l10n_es_facturae_face-17.0.1.0.1.1.dist-info/METADATA
odoo_addon_l10n_es_facturae_face-17.0.1.0.1.1.dist-info/WHEEL
odoo_addon_l10n_es_facturae_face-17.0.1.0.1.1.dist-info/top_level.txt
odoo_addon_l10n_es_facturae_face-17.0.1.0.1.1.dist-info/RECORD
