Metadata-Version: 2.1
Name: odoo-addon-l10n_es_facturae_face
Version: 17.0.1.0.1.1
Requires-Python: >=3.10
Requires-Dist: odoo-addon-edi_account_oca>=17.0dev,<17.1dev
Requires-Dist: odoo-addon-edi_exchange_template_oca>=17.0dev,<17.1dev
Requires-Dist: odoo-addon-l10n_es_facturae>=17.0dev,<17.1dev
Requires-Dist: odoo>=17.0a,<17.1dev
Summary: =?utf-8?q?Env=C3=ADo_de_Facturae_a_FACe?=
Home-page: https://github.com/OCA/l10n-spain
License: AGPL-3
Author: Creu Blanca, Odoo Community Association (OCA)
Author-email: support@odoo-community.org
Classifier: Programming Language :: Python
Classifier: Framework :: Odoo
Classifier: Framework :: Odoo :: 17.0
Classifier: License :: OSI Approved :: GNU Affero General Public License v3
